nonebot_plugin_tangkiller/__init__.py
nonebot_plugin_tangkiller/config.py
nonebot_plugin_tangkiller/tang.pt
nonebot_plugin_tangkiller-0.1.10.dist-info/LICENSE
nonebot_plugin_tangkiller-0.1.10.dist-info/METADATA
nonebot_plugin_tangkiller-0.1.10.dist-info/WHEEL
nonebot_plugin_tangkiller-0.1.10.dist-info/top_level.txt
nonebot_plugin_tangkiller-0.1.10.dist-info/RECORD
