Metadata-Version: 2.2
Name: nonebot-plugin-tangkiller
Version: 0.1.10
Summary: 识别糖菲，横扫唐气，做回自己。
License:                                  Apache License
Project-URL: Homepage, https://github.com/StillMisty/nonebot_plugin_tangkiller
Requires-Python: >=3.10
License-File: LICENSE
Requires-Dist: httpx>=0.27.0
Requires-Dist: nonebot-adapter-onebot>=2.4.6
Requires-Dist: nonebot2>=2.3
Requires-Dist: pillow>=10.0.0
Requires-Dist: ultralytics>=8.3.79
